commonlogging/__init__.py
common_logging-0.0.0.dist-info/LICENSE
common_logging-0.0.0.dist-info/METADATA
common_logging-0.0.0.dist-info/WHEEL
common_logging-0.0.0.dist-info/top_level.txt
common_logging-0.0.0.dist-info/RECORD
